AWSArchitectureBaseStack/AWSArchitectureBase.py
AWSArchitectureBaseStack/ArchitectureFlags.py
AWSArchitectureBaseStack/BBAWSLightsailMiniV1aDeploy.py
AWSArchitectureBaseStack/LightSailDomainAttachWrapper.py
AWSArchitectureBaseStack/LightSailPostDeploy.py
AWSArchitectureBaseStack/__init__.py
AWSArchitectureBaseStack/ftr_compliance.py
AWSArchitectureBaseStack/access_analyzer/__init__.py
AWSArchitectureBaseStack/access_analyzer/analyzer.py
AWSArchitectureBaseStack/backup/__init__.py
AWSArchitectureBaseStack/backup/iam_role.py
AWSArchitectureBaseStack/backup/plan.py
AWSArchitectureBaseStack/backup/resources.py
AWSArchitectureBaseStack/backup/s3_bucket.py
AWSArchitectureBaseStack/backup/vault.py
AWSArchitectureBaseStack/cloudtrail/__init__.py
AWSArchitectureBaseStack/cloudtrail/iam_role.py
AWSArchitectureBaseStack/cloudtrail/resources.py
AWSArchitectureBaseStack/cloudtrail/s3_bucket.py
AWSArchitectureBaseStack/cloudtrail/trail.py
AWSArchitectureBaseStack/config/__init__.py
AWSArchitectureBaseStack/config/recorder.py
AWSArchitectureBaseStack/config/resources.py
AWSArchitectureBaseStack/config/rules.py
AWSArchitectureBaseStack/config/s3_bucket.py
AWSArchitectureBaseStack/config/service_linked_role.py
AWSArchitectureBaseStack/ec2/__init__.py
AWSArchitectureBaseStack/ec2/ebs_encryption.py
AWSArchitectureBaseStack/guardduty/__init__.py
AWSArchitectureBaseStack/guardduty/detector.py
AWSArchitectureBaseStack/iam/__init__.py
AWSArchitectureBaseStack/iam/password_policy.py
AWSArchitectureBaseStack/iam/policy.py
AWSArchitectureBaseStack/iam/resources.py
AWSArchitectureBaseStack/iam/service.py
AWSArchitectureBaseStack/iam/service_roles.py
AWSArchitectureBaseStack/iam/support_role.py
AWSArchitectureBaseStack/iam/user.py
AWSArchitectureBaseStack/inspector/__init__.py
AWSArchitectureBaseStack/inspector/enablement.py
AWSArchitectureBaseStack/inspector/resources.py
AWSArchitectureBaseStack/kms/__init__.py
AWSArchitectureBaseStack/kms/key.py
awsarchitecturebase-0.17.0.dist-info/METADATA
awsarchitecturebase-0.17.0.dist-info/WHEEL
awsarchitecturebase-0.17.0.dist-info/top_level.txt
awsarchitecturebase-0.17.0.dist-info/RECORD
